jan_scraper/__init__.py
jan_scraper/__main__.py
jan_scraper/anylang.py
jan_scraper/conversator.py
jan_scraper/formatter.py
jan_scraper/langs.py
jan_scraper/models_source.py
jan_scraper/scraper.py
jan_scraper-0.1.0b1.dist-info/LICENSE
jan_scraper-0.1.0b1.dist-info/METADATA
jan_scraper-0.1.0b1.dist-info/WHEEL
jan_scraper-0.1.0b1.dist-info/top_level.txt
jan_scraper-0.1.0b1.dist-info/RECORD
