Metadata-Version: 2.1
Name: jan_scraper
Version: 0.1.0b1
Summary: jan_scraper: interact with Jan.ai by sending messages and retrieving the response
Author-email: Astra Bertelli <astra.bertelli01@universitadipavia.it>
License: GNU AFFERO GENERAL PUBLIC LICENSE
Project-URL: Homepage, https://github.com/AstraBert/jan-scraper
Project-URL: Issues, https://github.com/AstraBert/jan-scraper/issues
Classifier: Development Status :: 4 - Beta
Classifier: Intended Audience :: End Users/Desktop
Classifier: Programming Language :: Python :: 3
Classifier: License :: OSI Approved :: GNU Affero General Public License v3 or later (AGPLv3+)
Classifier: Operating System :: OS Independent
Requires-Python: >=3.10
License-File: LICENSE
Requires-Dist: pyautogui ==0.9.54
Requires-Dist: langdetect ==1.0.9
Requires-Dist: deep-translator ==1.11.4
Requires-Dist: transformers ==4.30.2
Requires-Dist: langchain-community ==0.0.13
Requires-Dist: langchain ==0.1.1
Requires-Dist: torch ==2.1.2
